bench/__init__.py
bench/test_combine.py
bench/test_delayed.py
bench/test_head.py
bench/test_worker.py
grain/__init__.py
grain/_version.py
grain/cli.py
grain/combine.py
grain/config.py
grain/conn.py
grain/conn2.py
grain/conn_msgp.py
grain/contextvar.py
grain/delayed.py
grain/head.py
grain/local_sworker.py
grain/pair.py
grain/remote_exer.py
grain/resource.py
grain/stat.py
grain/subproc.py
grain/subproc_worker.py
grain/test_combine.py
grain/test_conn2.py
grain/test_delayed.py
grain/test_head.py
grain/test_pair.py
grain/test_resource.py
grain/test_worker.py
grain/util.py
grain/worker.py
grain_scheduler-0.17.1.data/data/bin/gnaw
grain_scheduler-0.17.1.dist-info/LICENSE
grain_scheduler-0.17.1.dist-info/METADATA
grain_scheduler-0.17.1.dist-info/WHEEL
grain_scheduler-0.17.1.dist-info/entry_points.txt
grain_scheduler-0.17.1.dist-info/top_level.txt
grain_scheduler-0.17.1.dist-info/RECORD
