Metadata-Version: 2.1
Name: grain-scheduler
Version: 0.17.1
Summary: A scheduler for resource-aware parallel computing on clusters.
Home-page: https://github.com/Contextualist/grain
Author: Harry Zhang
Classifier: Development Status :: 4 - Beta
Classifier: Framework :: Trio
Classifier: Intended Audience :: Science/Research
Classifier: License :: OSI Approved :: MIT License
Classifier: Programming Language :: Python :: 3 :: Only
Classifier: Programming Language :: Python :: 3.9
Classifier: Programming Language :: Python :: 3.10
Classifier: Programming Language :: Python :: 3.11
Classifier: Programming Language :: Python :: 3.12
Classifier: Topic :: Scientific/Engineering
Classifier: Topic :: System :: Distributed Computing
Requires-Python: >=3.9
License-File: LICENSE
Requires-Dist: trio >=0.22.0
Requires-Dist: dill >=0.3.2
Requires-Dist: msgpack
Requires-Dist: attrs >=21.3.0
Requires-Dist: cattrs
Requires-Dist: click
Requires-Dist: psutil
Requires-Dist: tomli >=1.1.0 ; python_version < "3.11"
